doubletake/__init__.py
doubletake/searcher/__init__.py
doubletake/searcher/data_walker.py
doubletake/searcher/json_grepper.py
doubletake/searcher/string_replacer.py
doubletake/types/__init__.py
doubletake/types/settings.py
doubletake/utils/__init__.py
doubletake/utils/config_validator.py
doubletake/utils/data_faker.py
doubletake/utils/meta_match.py
doubletake/utils/pattern_manager.py
doubletake-1.1.0.dist-info/licenses/LICENSE
tests/__init__.py
tests/mocks/__init__.py
tests/mocks/test_data.py
tests/unit/__init__.py
tests/unit/test_init.py
tests/unit/searcher/__init__.py
tests/unit/searcher/test_data_walker.py
tests/unit/searcher/test_json_grepper.py
tests/unit/searcher/test_string_replacer.py
tests/unit/utils/__init__.py
tests/unit/utils/test_config_validator.py
tests/unit/utils/test_data_faker.py
tests/unit/utils/test_meta_match.py
tests/unit/utils/test_pattern_manager.py
doubletake-1.1.0.dist-info/METADATA
doubletake-1.1.0.dist-info/WHEEL
doubletake-1.1.0.dist-info/top_level.txt
doubletake-1.1.0.dist-info/RECORD
