Metadata-Version: 2.4
Name: doubletake
Version: 1.1.0
Summary: Intelligent PII detection and replacement for Python - automatically anonymize sensitive data in datasets, APIs, and logs
Home-page: https://github.com/dual/doubletake.git
Author: Paul Cruse III
Author-email: paulcruse3@gmail.com
License: Apache 2.0
Project-URL: Homepage, https://github.com/dual/doubletake
Project-URL: Documentation, https://github.com/dual/doubletake#readme
Project-URL: Source Code, https://github.com/dual/doubletake
Project-URL: Bug Reports, https://github.com/dual/doubletake/issues
Project-URL: Funding, https://github.com/sponsors/dual
Project-URL: CI/CD, https://circleci.com/gh/dual/doubletake
Keywords: pii,privacy,gdpr,data-anonymization,data-masking,sensitive-data,email-scrubbing,phone-anonymization,ssn-masking,credit-card-protection,faker,synthetic-data,compliance,security,data-protection,regex-patterns,json-processing,api-sanitization,log-anonymization,testing-data,development-tools,database-anonymization
Platform: any
Classifier: Development Status :: 4 - Beta
Classifier: Intended Audience :: Developers
Classifier: Intended Audience :: System Administrators
Classifier: Intended Audience :: Information Technology
Classifier: Intended Audience :: Financial and Insurance Industry
Classifier: Intended Audience :: Healthcare Industry
Classifier: Intended Audience :: Legal Industry
Classifier: License :: OSI Approved :: Apache Software License
Classifier: Environment :: Web Environment
Classifier: Environment :: Console
Classifier: Operating System :: OS Independent
Classifier: Programming Language :: Python
Classifier: Programming Language :: Python :: 3
Classifier: Programming Language :: Python :: 3.9
Classifier: Programming Language :: Python :: 3.10
Classifier: Programming Language :: Python :: 3.11
Classifier: Programming Language :: Python :: 3.12
Classifier: Programming Language :: Python :: 3 :: Only
Classifier: Topic :: Security
Classifier: Topic :: Security :: Cryptography
Classifier: Topic :: Software Development :: Libraries :: Python Modules
Classifier: Topic :: Software Development :: Testing
Classifier: Topic :: Software Development :: Quality Assurance
Classifier: Topic :: Internet :: WWW/HTTP :: Dynamic Content
Classifier: Topic :: Database
Classifier: Topic :: Text Processing :: Filters
Classifier: Topic :: Scientific/Engineering :: Information Analysis
Classifier: Topic :: System :: Systems Administration
Classifier: Topic :: Utilities
Classifier: Natural Language :: English
Classifier: Typing :: Typed
Requires-Python: >=3.9
License-File: LICENSE
Requires-Dist: faker
Requires-Dist: msgspec
Requires-Dist: typing_extensions
Dynamic: author
Dynamic: author-email
Dynamic: classifier
Dynamic: description
Dynamic: description-content-type
Dynamic: home-page
Dynamic: keywords
Dynamic: license
Dynamic: license-file
Dynamic: platform
Dynamic: project-url
Dynamic: requires-dist
Dynamic: requires-python
Dynamic: summary
